{"tweet_urls":[],"text_en":"RT @BracketBattles1: Greatest Active NFL QB\n\u2022 SWEET 16 \u2022\n\nRT ~ Ben Roethlisberger\nFav ~ Carson Palmer http://t.co/5IvCxrIsQM","created_at":"2015-09-19T21:58:25Z","id":"645416692412219392","lang":"en","tweet_hashtags":[]},{"tweet_urls":["http://ow.ly/SqOnd"],"text_en":"Put Dr. Ben Carson in charge of cleaning up the VA to correct this outrage. http://t.co/TuJluzGA66","created_at":"2015-09-19T21:58:14Z","id":"645416647969349632","lang":"en","tweet_hashtags":[]},{"tweet_urls":["http://thinkingmomsrevolution.com/did-dr-ben-carson-just-let-the-cat-out-of-the-bag/"],"text_en":"Do you #HearUs now? The cat is out of the bag! @jasoninthehouse investigate #CDCwhistleblower \nhttp://t.co/gCICVTUee1","created_at":"2015-09-19T21:57:45Z","id":"645416523918651392","lang":"en","tweet_hashtags":["HearUs","CDCwhistleblower"]},{"tweet_urls":["http://theweek.com/articles/577834/ben-carson-total-snooze-thats-good-thing"],"text_en":"Carson's mellowness is a feature not a bug #Carson2016 http://t.co/EaGTbypfpw","created_at":"2015-09-19T21:57:37Z","id":"645416492826124289","lang":"en","tweet_hashtags":["Carson2016"]},{"tweet_urls":[],"text_en":"RT @BracketBattles1: Greatest Active NFL QB\n\u2022 SWEET 16 \u2022\n\nRT ~ Ben Roethlisberger\nFav ~ Carson Palmer http://t.co/5IvCxrIsQM","created_at":"2015-09-19T21:57:20Z","id":"645416421946728449","lang":"en","tweet_hashtags":[]},{"tweet_urls":["https://twitter.com/marcacaputo/status/645408246996578304"],"text_en":"Did they ask him about his successor Ben Carson? https://t.co/3EkSYctmzp","created_at":"2015-09-19T21:56:59Z","id":"645416331039404032","lang":"en","tweet_hashtags":[]},{"tweet_urls":["http://thinkingmomsrevolution.com/did-dr-ben-carson-just-let-the-cat-out-of-the-bag/"],"text_en":"#HearUs the cat is out of the bag! Thank you @realDonaldTrump ask #CDCwhistleblower \nhttp://t.co/gCICVTUee1","created_at":"2015-09-19T21:56:25Z","id":"645416189880082432","lang":"en","tweet_hashtags":["HearUs","CDCwhistleblower"]},{"tweet_urls":[],"text_en":"@BeforeDarkness @JohnnySoftware Whites as a group score better than blacks in any known academic measurement. Ben Carson is an outlier.","created_at":"2015-09-19T21:56:12Z","id":"645416135727300608","lang":"en","tweet_hashtags":[]},{"tweet_urls":[],"text_en":"RT @BracketBattles1: Greatest Active NFL QB\n\u2022 SWEET 16 \u2022\n\nRT ~ Ben Roethlisberger\nFav ~ Carson Palmer http://t.co/5IvCxrIsQM","created_at":"2015-09-19T21:56:11Z","id":"645416129326788609","lang":"en","tweet_hashtags":[]},{"tweet_urls":["http://dlvr.it/CCMTqF"],"text_en":"Medical community criticizes Carson and Paul's view on vaccines - CNN http://t.co/6DNi32J7zT","created_at":"2015-09-19T21:55:37Z","id":"645415988976992257","lang":"en","tweet_hashtags":[]},{"tweet_urls":["http://thinkingmomsrevolution.com/did-dr-ben-carson-just-let-the-cat-out-of-the-bag/"],"text_en":"@CNNPolitics the cat is out of the bag!!\nThank you! @RandPaul @realDonaldTrump @RealBenCarson ask #CDCwhistleblower \nhttp://t.co/gCICVTUee1","created_at":"2015-09-19T21:54:38Z","id":"645415742771437568","lang":"en","tweet_hashtags":["CDCwhistleblower"]},{"tweet_urls":["http://cnn.it/1MbeQuU"],"text_en":"RT @RealBenCarson: We're closing in on first place! \"New Hampshire poll: Ben Carson within 4 points of Donald Trump\" http://t.co/cTcHvWWCyK\u2026","created_at":"2015-09-19T21:54:26Z","id":"645415691785400320","lang":"en","tweet_hashtags":[]},{"tweet_urls":[],"text_en":"RT @BracketBattles1: Greatest Active NFL QB\n\u2022 SWEET 16 \u2022\n\nRT ~ Ben Roethlisberger\nFav ~ Carson Palmer http://t.co/5IvCxrIsQM","created_at":"2015-09-19T21:54:11Z","id":"645415627386044416","lang":"en","tweet_hashtags":[]},{"tweet_urls":[],"text_en":"RT @BracketBattles1: Greatest Active NFL QB\n\u2022 SWEET 16 \u2022\n\nRT ~ Ben Roethlisberger\nFav ~ Carson Palmer http://t.co/5IvCxrIsQM","created_at":"2015-09-19T21:54:00Z","id":"645415580091199488","lang":"en","tweet_hashtags":[]},{"tweet_urls":["http://s.mlive.com/2thLThk"],"text_en":"RT @RealBenCarson: \"Excitement high among Republicans for Ben Carson's visit to Jackson\" http://t.co/xXFbvVlUi1 via @mlive","created_at":"2015-09-19T21:53:53Z","id":"645415552656216064","lang":"en","tweet_hashtags":[]},{"tweet_urls":[],"text_en":"We have the ability to do it. We don't have the will to do it.  -  Ben Carson #prettymuchsumsupournationunderthispresident","created_at":"2015-09-19T21:53:34Z","id":"645415474201821184","lang":"en","tweet_hashtags":["prettymuchsumsupournationunderthispresident"]},{"tweet_urls":[],"text_en":"RT @DraftRunBenRun: \"The US should use every resource available to destroy\u201d global jihadists before they destroy the U.S. - Ben Carson","created_at":"2015-09-19T21:53:29Z","id":"645415453418987520","lang":"en","tweet_hashtags":[]},{"tweet_urls":["http://gu.com/p/4bkxg/stw"],"text_en":"Ben Carson: understated candidate quietly rises in polls amid Trump frenzy http://t.co/2t0k7zRMp5","created_at":"2015-09-19T21:53:06Z","id":"645415356073406464","lang":"en","tweet_hashtags":[]},{"tweet_urls":["http://thebea.st/1QohaQ5"],"text_en":"RT @emilyinnocent21: It\u2019s Time to Pull the Plug on Dr. Ben Carson\u2019s Campaign http://t.co/BmtZchOsCC via @thedailybeast","created_at":"2015-09-19T21:52:06Z","id":"645415103492296710","lang":"en","tweet_hashtags":[]},{"tweet_urls":["http://thinkingmomsrevolution.com/did-dr-ben-carson-just-let-the-cat-out-of-the-bag/"],"text_en":"RT @ProParentRights: Did Dr. Ben Carson Just Let the Cat out of the Bag? http://t.co/GeQqoUb7ys #HearThisWell #CDCWhistleblower #GOPDebates\u2026","created_at":"2015-09-19T21:51:07Z","id":"645414855260835841","lang":"en","tweet_hashtags":["HearThisWell","CDCWhistleblower","GOPDebates","ReligiousFreedom"]},{"tweet_urls":[],"text_en":"RT @BracketBattles1: Greatest Active NFL QB\n\u2022 SWEET 16 \u2022\n\nRT ~ Ben Roethlisberger\nFav ~ Carson Palmer http://t.co/5IvCxrIsQM","created_at":"2015-09-19T21:50:54Z","id":"645414802735689728","lang":"en","tweet_hashtags":[]},{"tweet_urls":["http://hill.cm/pi3GJTr"],"text_en":"RT @thehill: Ben Carson wants Congress to call Obama's bluff on Planned Parenthood: http://t.co/ZPvE9w9Prn http://t.co/Gs9Lpd2iG1","created_at":"2015-09-19T21:50:10Z","id":"645414614860083200","lang":"en","tweet_hashtags":[]},{"tweet_urls":[],"text_en":"CNN in their coverage forever ignoring Ben Carson as a candidate. Seem as if the Obama effect has dampered his chance as a black man. Hush","created_at":"2015-09-19T21:49:52Z","id":"645414540042043392","lang":"en","tweet_hashtags":[]},{"tweet_urls":["http://www.politifact.com/florida/statements/2015/sep/17/ben-carson/ben-carson-says-pediatricians-realize-need-cut-dow/"],"text_en":"#pantsonfire - #Carson says pediatricians realize need to cut down number and proximity of #vaccines http://t.co/ZrwhjnKkSd","created_at":"2015-09-19T21:49:49Z","id":"645414529732448256","lang":"en","tweet_hashtags":["pantsonfire","Carson","vaccines"]},{"tweet_urls":[],"text_en":"@KLSouth @FoxNews Opps, you forgot Dr Ben Carson... He was favored for a whole day going into CNN debate...lol","created_at":"2015-09-19T21:49:44Z","id":"645414509474091008","lang":"en","tweet_hashtags":[]},{"tweet_urls":["http://s.mlive.com/2thLThk"],"text_en":"RT @RealBenCarson: \"Excitement high among Republicans for Ben Carson's visit to Jackson\" http://t.co/xXFbvVlUi1 via @mlive","created_at":"2015-09-19T21:49:24Z","id":"645414425181220864","lang":"en","tweet_hashtags":[]},{"tweet_urls":["http://tinyurl.com/onoqob5"],"text_en":"RT @ShamrockTTMR: @drsanjaygupta @CNNPolitics @realDonaldTrump Thank you all 4 letting the cat out of the bag! @RealBenCarson http://t.co/g\u2026","created_at":"2015-09-19T21:48:47Z","id":"645414266686828544","lang":"en","tweet_hashtags":[]},{"tweet_urls":["http://tinyurl.com/onoqob5"],"text_en":"RT @ShamrockTTMR: @drsanjaygupta @CNNPolitics @realDonaldTrump  @RealBenCarson Thank you all 4 letting the cat out of the bag! http://t.co/\u2026","created_at":"2015-09-19T21:48:45Z","id":"645414258184994817","lang":"en","tweet_hashtags":["sb277"]},{"tweet_urls":["http://thebea.st/1QohaQ5"],"text_en":"It\u2019s Time to Pull the Plug on Dr. Ben Carson\u2019s Campaign http://t.co/BmtZchOsCC via @thedailybeast","created_at":"2015-09-19T21:48:17Z","id":"645414143038763012","lang":"en","tweet_hashtags":[]},{"tweet_urls":[],"text_en":"RT @missrepub: 'Thinking about Ben Carson being president' http://t.co/IzXN0H8MRy","created_at":"2015-09-19T21:48:12Z","id":"645414122415370240","lang":"en","tweet_hashtags":[]},{"tweet_urls":["http://thinkingmomsrevolution.com/did-dr-ben-carson-just-let-the-cat-out-of-the-bag/"],"text_en":"RT @VaccineChoiceCA: Did Dr. Ben Carson Just Let the Cat out of the Bag? - Thinking Moms' Revolution http://t.co/xtxceQfQvJ","created_at":"2015-09-19T21:48:00Z","id":"645414072268255232","lang":"en","tweet_hashtags":[]},{"tweet_urls":[],"text_en":"@OneNation4Ben Ben is the one! Vote Ben Carson for president!","created_at":"2015-09-19T21:47:59Z","id":"645414067230760960","lang":"en","tweet_hashtags":[]},{"tweet_urls":["http://thinkingmomsrevolution.com/did-dr-ben-carson-just-let-the-cat-out-of-the-bag/"],"text_en":"RT @ProParentRights: Did Dr. Ben Carson Just Let the Cat out of the Bag? http://t.co/GeQqoUb7ys #HearThisWell #CDCWhistleblower #GOPDebates\u2026","created_at":"2015-09-19T21:47:55Z","id":"645414051833450497","lang":"en","tweet_hashtags":["HearThisWell","CDCWhistleblower","GOPDebates","ReligiousFreedom"]},{"tweet_urls":["http://thinkingmomsrevolution.com/did-dr-ben-carson-just-let-the-cat-out-of-the-bag/"],"text_en":"RT @ProParentRights: Did Dr. Ben Carson Just Let the Cat out of the Bag? http://t.co/GeQqoUb7ys #HearThisWell #CDCWhistleblower #GOPDebates\u2026","created_at":"2015-09-19T21:47:44Z","id":"645414005968912384","lang":"en","tweet_hashtags":["HearThisWell","CDCWhistleblower","GOPDebates","ReligiousFreedom"]},{"tweet_urls":["http://thebea.st/1LpQCyz"],"text_en":"\"the part of America filled with funk and failure. This is the America where political pundits reside.\"  http://t.co/ZpqXt5xH26","created_at":"2015-09-19T21:47:13Z","id":"645413876155023361","lang":"en","tweet_hashtags":[]},{"tweet_urls":["http://ln.is/thedailybeast.com/L18xj"],"text_en":"He's too good for this: It\u2019s Time to Pull the Plug on Dr. Ben Carson\u2019s Campaign http://t.co/IwyWyweoAu via @thedailybeast","created_at":"2015-09-19T21:47:01Z","id":"645413823281803268","lang":"en","tweet_hashtags":[]},{"tweet_urls":["http://www.pollitical.com/933/"],"text_en":"RT @PolliticalCom: Trump is an easy target for the Democrats. Ben Carson? Not so much. Here's why:\n\nhttp://t.co/FTkJrED9Ze\n\n. http://t.co/l\u2026","created_at":"2015-09-19T21:46:56Z","id":"645413802880536576","lang":"en","tweet_hashtags":[]},{"tweet_urls":["http://thebea.st/1QohaQ5"],"text_en":"It\u2019s Time to Pull the Plug on Dr. Ben Carson\u2019s Campaign http://t.co/FMdvDuucnW via @thedailybeast","created_at":"2015-09-19T21:45:56Z","id":"645413551218163712","lang":"en","tweet_hashtags":[]},{"tweet_urls":[],"text_en":"RT @trumpgasm: POST DEBATE POLL:\nDONALD TRUMP MOVES UP,\nBEN CARSON MOVES DOWN,\nEVERYONE ELSE IN SINGLE DIGITS:\nTHE END.\n#TRUMPGASM http://t\u2026","created_at":"2015-09-19T21:45:49Z","id":"645413523355475969","lang":"en","tweet_hashtags":["TRUMPGASM"]},{"tweet_urls":[],"text_en":"@cucksbeware @BeforeDarkness I think we mostly agree that Ben Carson, Obama, his physicist brother are SMARTER than us. They ARE measured.","created_at":"2015-09-19T21:45:33Z","id":"645413454753492992","lang":"en","tweet_hashtags":[]},{"tweet_urls":["http://youtu.be/QUhENfOmX6I?a"],"text_en":"I liked a @YouTube video http://t.co/mvcLwfiKHm Full Speech: Ben Carson Speaks at Heritage Action Presidential Forum (9-18-15)","created_at":"2015-09-19T21:45:05Z","id":"645413335433740288","lang":"en","tweet_hashtags":[]},{"tweet_urls":[],"text_en":"RT @onlinewweman: Ben Carson tried stabbing a kid in the abdomen when he was 14. Then he decided he'd rather stab people's heads and become\u2026","created_at":"2015-09-19T21:45:01Z","id":"645413322658070528","lang":"en","tweet_hashtags":[]},{"tweet_urls":["http://ift.tt/1KsVVYZ"],"text_en":"RT @HouseOfHorrorz: #read #book #ebay #auction http://t.co/iIxYDwtEjF Gifted Hands- The Ben Carson Story  (SKU: G0061042536I5N00) http://t.\u2026","created_at":"2015-09-19T21:44:53Z","id":"645413287086002176","lang":"en","tweet_hashtags":["read","book","ebay","auction"]},{"tweet_urls":[],"text_en":"RT @trumpgasm: POST DEBATE POLL:\nDONALD TRUMP MOVES UP,\nBEN CARSON MOVES DOWN,\nEVERYONE ELSE IN SINGLE DIGITS:\nTHE END.\n#TRUMPGASM http://t\u2026","created_at":"2015-09-19T21:44:50Z","id":"645413272984928256","lang":"en","tweet_hashtags":["TRUMPGASM"]},{"tweet_urls":[],"text_en":"I forgot Ben Carson was my cousins doctor.","created_at":"2015-09-19T21:44:21Z","id":"645413152688054272","lang":"en","tweet_hashtags":[]},{"tweet_urls":["http://po.st/rVMQvS"],"text_en":"CNN Reporter Says It Is Ok To Abort Babies, Dr. Ben Carson\u2019s Response Is Epic! http://t.co/71m6BRmU4w via @po_st","created_at":"2015-09-19T21:43:45Z","id":"645413002460667904","lang":"en","tweet_hashtags":[]},{"tweet_urls":["http://bit.ly/1LnnfNt"],"text_en":"CafePress had a better IP lawyer - Carson tries to sue people making Ben Carson for President T-shirts, fails\nhttp://t.co/hhDqDC7zeK","created_at":"2015-09-19T21:43:31Z","id":"645412941534072832","lang":"en","tweet_hashtags":[]},{"tweet_urls":[],"text_en":"RT @BracketBattles1: Greatest Active NFL QB\n\u2022 SWEET 16 \u2022\n\nRT ~ Ben Roethlisberger\nFav ~ Carson Palmer http://t.co/5IvCxrIsQM","created_at":"2015-09-19T21:43:26Z","id":"645412923137990656","lang":"en","tweet_hashtags":[]},{"tweet_urls":[],"text_en":"If I could have anyone be our president it'd be Ben Carson. But he's too soft gah damn it","created_at":"2015-09-19T21:43:07Z","id":"645412842464747520","lang":"en","tweet_hashtags":[]},{"tweet_urls":["http://thebea.st/1QohaQ5"],"text_en":"Ben Carson is brilliant and kind. Therefore, he has no business running for president. http://t.co/RjkeCHBwWh via @thedailybeast","created_at":"2015-09-19T21:42:22Z","id":"645412654446702592","lang":"en","tweet_hashtags":[]},{"tweet_urls":[],"text_en":"@NETRetired i don't think nobody thinks Dr.Ben Carson is Gay","created_at":"2015-09-19T21:42:11Z","id":"645412605608206336","lang":"en","tweet_hashtags":[]},{"tweet_urls":["http://nyti.ms/1KQSVvX"],"text_en":"http://t.co/54gb95RZ6S\nAs Madea says HAL LAY YOU YER!  It's time that the Republican own up to the fact that it is a Party of Racists.","created_at":"2015-09-19T21:42:00Z","id":"645412559638556672","lang":"en","tweet_hashtags":[]},{"tweet_urls":["http://www.whodoyoulike2016.com/gop/ben-carson/with-ben-carson-surging-and-trump-rising-steadily-we-could-see-a-repeat-of-ij-review"],"text_en":"With Ben Carson Surging and Trump Rising Steadily, We Could See a Repeat of \u2026 \u2013 IJ Review http://t.co/5VmF1sZQOs","created_at":"2015-09-19T21:41:07Z","id":"645412339852836864","lang":"en","tweet_hashtags":[]},{"tweet_urls":[],"text_en":"@cnnbrk  Ben Carson is a doctor on the vaccinogen board and he should know that vaccines need to be spaced out! #sb277referendum","created_at":"2015-09-19T21:40:44Z","id":"645412242352046080","lang":"en","tweet_hashtags":["sb277referendum"]},{"tweet_urls":["http://cue.li/a3por"],"text_en":"At Ben Carson Debate Watch Party, Pulled Pork And Plenty Of Awkward Silences http://t.co/zvmIww2JDj http://t.co/bWOE6jhO7R","created_at":"2015-09-19T21:40:07Z","id":"645412085833203712","lang":"en","tweet_hashtags":[]},{"tweet_urls":["http://mhyatt.us/1QJJY6n"],"text_en":"The Secret to Ben Carson\u2019s Success http://t.co/CmdREU8F0C via @michaelhyatt","created_at":"2015-09-19T21:40:06Z","id":"645412082578554880","lang":"en","tweet_hashtags":[]},{"tweet_urls":[],"text_en":"@McCormickJohn hahahaha, @RealBenCarson may be a political putz but @scottwalker lacks the smarts to be Ben Carson. Or any type of surgeon.","created_at":"2015-09-19T21:39:42Z","id":"645411981881683968","lang":"en","tweet_hashtags":[]},{"tweet_urls":[],"text_en":"RT @BracketBattles1: Greatest Active NFL QB\n\u2022 SWEET 16 \u2022\n\nRT ~ Ben Roethlisberger\nFav ~ Carson Palmer http://t.co/5IvCxrIsQM","created_at":"2015-09-19T21:39:39Z","id":"645411972004093953","lang":"en","tweet_hashtags":[]},{"tweet_urls":["http://bit.ly/1QOZAWi"],"text_en":"RT @ijreview: With Ben Carson Surging and Trump Rising Steadily, We Could See a Repeat of the GOP 2012 Primary http://t.co/uSeOszDaVF","created_at":"2015-09-19T21:39:33Z","id":"645411945902796800","lang":"en","tweet_hashtags":[]},{"tweet_urls":["http://www.cnn.com/2015/09/18/politics/ben-carson-donald-trump-muslims/index.html"],"text_en":"RT @jaketapper: Carson jokes about Trump dropping out of race http://t.co/IVkWf2v9gr","created_at":"2015-09-19T21:39:16Z","id":"645411875400736772","lang":"en","tweet_hashtags":[]},{"tweet_urls":[],"text_en":"RT @BracketBattles1: Greatest Active NFL QB\n\u2022 SWEET 16 \u2022\n\nRT ~ Ben Roethlisberger\nFav ~ Carson Palmer http://t.co/5IvCxrIsQM","created_at":"2015-09-19T21:38:44Z","id":"645411740256223233","lang":"en","tweet_hashtags":[]},{"tweet_urls":["http://www.pollitical.com/933/"],"text_en":"RT @PolliticalCom: Trump is an easy target for the Democrats. Ben Carson? Not so much. Here's why:\n\nhttp://t.co/FTkJrED9Ze\n\n. http://t.co/l\u2026","created_at":"2015-09-19T21:38:37Z","id":"645411711642652672","lang":"en","tweet_hashtags":[]},{"tweet_urls":["http://fb.me/4CrhvEVK2"],"text_en":"Many of us have sons and daughters who will not get into medical school or start a business, join the military,... http://t.co/IxJaqOvNzh","created_at":"2015-09-19T21:37:48Z","id":"645411502837534720","lang":"en","tweet_hashtags":[]},{"tweet_urls":[],"text_en":"RT @scalzi: An immediate entry into the OH SNAP Hall of Fame, from California Gov. Jerry Brown to Ben Carson. http://t.co/7gKv4cZmHS","created_at":"2015-09-19T21:37:04Z","id":"645411320938917888","lang":"en","tweet_hashtags":[]},{"tweet_urls":[],"text_en":"RT @BracketBattles1: Greatest Active NFL QB\n\u2022 SWEET 16 \u2022\n\nRT ~ Ben Roethlisberger\nFav ~ Carson Palmer http://t.co/5IvCxrIsQM","created_at":"2015-09-19T21:36:56Z","id":"645411288353341441","lang":"en","tweet_hashtags":[]},{"tweet_urls":["https://twitter.com/byamberphillips/status/644333734074916864"],"text_en":"RT @DanteAtkins: Donald Trump wants to high-five. Ben Carson just wants to avoid any physical contact whatsoever. This is hilarious. https:\u2026","created_at":"2015-09-19T21:36:56Z","id":"645411287548100609","lang":"en","tweet_hashtags":[]},{"tweet_urls":["http://ift.tt/1KB7Jg5"],"text_en":"Surgery, celebrity and CPAC: Ben Carson's path to a presidential bid - Politico http://t.co/8yVvSvvzIo #bencarson\u2026 http://t.co/xFyA98MkDM","created_at":"2015-09-19T21:36:46Z","id":"645411243461865472","lang":"en","tweet_hashtags":["bencarson"]},{"tweet_urls":["http://louderwithcrowder.com/mickey-rourke-emphatically-endorses-ben-carson-for-president/"],"text_en":"RT @scrowder: Surprised? => Mickey Rourke Emphatically Endorses Ben Carson for President! http://t.co/bvp5B2Ev9v","created_at":"2015-09-19T21:36:28Z","id":"645411167070908416","lang":"en","tweet_hashtags":[]},{"tweet_urls":["http://www.ijreview.com/2015/09/421561-ben-carson-surging-trump-rising-steadily-seeing-repeat-2012/?utm_content=buffer0fe73&utm_medium=social&utm_source=twitter.com&utm_campaign=buffer"],"text_en":"Prediction: poll lead will go Trump, then Carson, then Fiorina, then Marco Rubio http://t.co/PXN0ttwmSy","created_at":"2015-09-19T21:35:26Z","id":"645410909045850112","lang":"en","tweet_hashtags":[]},{"tweet_urls":["http://bit.ly/1Mu8ObO"],"text_en":"RT @natureovernewz: California's governor sent a letter to Republican candidate Ben Carson ... - Business Insider http://t.co/GBSEEr6AFO ht\u2026","created_at":"2015-09-19T21:35:23Z","id":"645410895905050624","lang":"en","tweet_hashtags":[]},{"tweet_urls":["http://fb.me/2k2PPp2hB"],"text_en":"Manos Milagrosas La Historia del Dr Ben Carson Gifted Hands... http://t.co/wYyb7aGuuY","created_at":"2015-09-19T21:35:07Z","id":"645410829198716928","lang":"en","tweet_hashtags":[]},{"tweet_urls":["http://fb.me/4aUoZAJFo"],"text_en":"Manos Milagrosas La Historia del Dr Ben Carson Gifted Hands... http://t.co/RtpoW0Mnr1","created_at":"2015-09-19T21:35:06Z","id":"645410823913926656","lang":"en","tweet_hashtags":[]},{"tweet_urls":[],"text_en":"Finally watched the second republican debate. Faves Carly Fiorina, Marco Rubio, John Kasich, and Ben Carson.","created_at":"2015-09-19T21:34:57Z","id":"645410786597179392","lang":"en","tweet_hashtags":[]},{"tweet_urls":[],"text_en":"I just watched a video with Dr Ben Carson endorsing health equity. Wtf????","created_at":"2015-09-19T21:34:57Z","id":"645410786358243328","lang":"en","tweet_hashtags":[]},{"tweet_urls":["http://tinyurl.com/onoqob5"],"text_en":"RT @ShamrockTTMR: @drsanjaygupta @CNNPolitics @realDonaldTrump Thank you all 4 letting the cat out of the bag! @RealBenCarson http://t.co/g\u2026","created_at":"2015-09-19T21:34:54Z","id":"645410776430346242","lang":"en","tweet_hashtags":[]},{"tweet_urls":["http://tinyurl.com/onoqob5"],"text_en":"RT @ShamrockTTMR: @drsanjaygupta @CNNPolitics @realDonaldTrump  @RealBenCarson Thank you all 4 letting the cat out of the bag! http://t.co/\u2026","created_at":"2015-09-19T21:34:50Z","id":"645410757610500096","lang":"en","tweet_hashtags":["sb277"]},{"tweet_urls":["http://dlvr.it/CCMKtX"],"text_en":"Carson jokes about Trump dropping out: Republican presidential candidate Ben Carson celebrated his birthday Friday\u2026 http://t.co/zeBPESvSJ5","created_at":"2015-09-19T21:34:47Z","id":"645410745736278016","lang":"en","tweet_hashtags":[]},{"tweet_urls":["http://dlvr.it/CCMDnF"],"text_en":"Carson jokes about Trump dropping out http://t.co/l9TcXh4rnb","created_at":"2015-09-19T21:34:46Z","id":"645410740891881472","lang":"en","tweet_hashtags":[]},{"tweet_urls":["http://dlvr.it/CCMHQJ"],"text_en":"Carson jokes about Trump dropping out: Republican presidential candidate Ben Carson celebrated his birthday Friday\u2026 http://t.co/ILIJ2OK4WN","created_at":"2015-09-19T21:34:42Z","id":"645410722843766784","lang":"en","tweet_hashtags":[]},{"tweet_urls":["http://thebea.st/1QohaQ5"],"text_en":"It\u2019s Time to Pull the Plug on Dr. Ben Carson\u2019s Campaign http://t.co/pqJl1lEvcW via @thedailybeast","created_at":"2015-09-19T21:34:19Z","id":"645410626404225024","lang":"en","tweet_hashtags":[]},{"tweet_urls":[],"text_en":"I have hope in our nation because of Dr. Ben Carson.","created_at":"2015-09-19T21:34:01Z","id":"645410552819281920","lang":"en","tweet_hashtags":[]},{"tweet_urls":[],"text_en":"RT @trumpgasm: POST DEBATE POLL:\nDONALD TRUMP MOVES UP,\nBEN CARSON MOVES DOWN,\nEVERYONE ELSE IN SINGLE DIGITS:\nTHE END.\n#TRUMPGASM http://t\u2026","created_at":"2015-09-19T21:33:56Z","id":"645410530388262912","lang":"en","tweet_hashtags":["TRUMPGASM"]},{"tweet_urls":["http://thinkingmomsrevolution.com/did-dr-ben-carson-just-let-the-cat-out-of-the-bag/"],"text_en":"Did Dr. Ben Carson Just Let the Cat out of the Bag? http://t.co/GeQqoUb7ys #HearThisWell #CDCWhistleblower #GOPDebates #ReligiousFreedom","created_at":"2015-09-19T21:33:17Z","id":"645410369083576320","lang":"en","tweet_hashtags":["HearThisWell","CDCWhistleblower","GOPDebates","ReligiousFreedom"]},{"tweet_urls":["http://bit.ly/1Mu8ObO"],"text_en":"RT @natureovernewz: California's governor sent a letter to Republican candidate Ben Carson ... - Business Insider http://t.co/GBSEEr6AFO ht\u2026","created_at":"2015-09-19T21:32:50Z","id":"645410255216726016","lang":"en","tweet_hashtags":[]},{"tweet_urls":[],"text_en":"RT @macandlinuxuser: @JudgeJeanine When it's all said and done, Carly Fiorina and Ben Carson are the best choice.  Good show.","created_at":"2015-09-19T21:31:06Z","id":"645409819373867008","lang":"en","tweet_hashtags":[]},{"tweet_urls":["http://bit.ly/1JPTBjb"],"text_en":"Satiristas: RT toddbarry: Ben Carson looks at his notes more than an alt comic.  #GOPDebate http://t.co/AuhlNZa3Ww","created_at":"2015-09-19T21:31:05Z","id":"645409813229371392","lang":"en","tweet_hashtags":["GOPDebate"]},{"tweet_urls":["http://bit.ly/1QOZAWi"],"text_en":"With Ben Carson Surging and Trump Rising Steadily, We Could See a Repeat of the GOP 2012 Primary http://t.co/uSeOszDaVF","created_at":"2015-09-19T21:30:28Z","id":"645409660648976385","lang":"en","tweet_hashtags":[]},{"tweet_urls":[],"text_en":"RT @authorclaire1: @amentilone ya I'm going to write him in, I can't remember who I wanted 4 VP. Allen West for DoD. Ben Carson for surgeon\u2026","created_at":"2015-09-19T21:30:05Z","id":"645409562565156865","lang":"en","tweet_hashtags":[]},{"tweet_urls":[],"text_en":"RT @toddbarry: Ben Carson looks at his notes more than an alt comic.  #GOPDebate","created_at":"2015-09-19T21:30:02Z","id":"645409549436891136","lang":"en","tweet_hashtags":["GOPDebate"]},{"tweet_urls":[],"text_en":"@amentilone ya I'm going to write him in, I can't remember who I wanted 4 VP. Allen West for DoD. Ben Carson for surgeon general.","created_at":"2015-09-19T21:29:38Z","id":"645409448735862784","lang":"en","tweet_hashtags":[]},{"tweet_urls":["http://buff.ly/1GXqJAi"],"text_en":"RT @Norsu2: Carson in Iowa: Use oil subsidies for ethanol http://t.co/ZAs4HoIc1k Ben wants 30% ethanol blends, subsidies #tcot No Ben No #f\u2026","created_at":"2015-09-19T21:29:36Z","id":"645409440607264768","lang":"en","tweet_hashtags":["tcot","fitn"]},{"tweet_urls":[],"text_en":"RT @BracketBattles1: Greatest Active NFL QB\n\u2022 SWEET 16 \u2022\n\nRT ~ Ben Roethlisberger\nFav ~ Carson Palmer http://t.co/5IvCxrIsQM","created_at":"2015-09-19T21:29:33Z","id":"645409426279673856","lang":"en","tweet_hashtags":[]},{"tweet_urls":["http://www.nbc.com/the-tonight-show/video/republican-candidate-ben-carson-turns-64-pope-francis-visits-us-monologue/2909040"],"text_en":"RT @FallonTonight: \"I saw that Jeb Bush is trying to backpedal away from his answer that British Prime...\" http://t.co/ChYrG7dTWv http://t.\u2026","created_at":"2015-09-19T21:29:04Z","id":"645409307878490112","lang":"en","tweet_hashtags":[]},{"tweet_urls":["https://youtu.be/ilSoDJij6SI"],"text_en":"Dr. Ben Carson Gets It Wrong On Vaccine Question https://t.co/GYf5Y0bRTC via @YouTube","created_at":"2015-09-19T21:28:50Z","id":"645409247845576704","lang":"en","tweet_hashtags":[]},{"tweet_urls":["http://twitter.com/mdsdaily/status/645406049374093312","http://bit.ly/1iFvFol"],"text_en":"RT http://t.co/P5Cgmc3hvw Medical community criticizes Carson and Paul's view on vaccines - CNN http://t.co/HAIr0rMACS #medical #science","created_at":"2015-09-19T21:28:42Z","id":"645409214937083905","lang":"en","tweet_hashtags":["medical","science"]},{"tweet_urls":[],"text_en":"How about a Carley/Carson ticket?!  Ben could be her vice-president. #2016","created_at":"2015-09-19T21:28:32Z","id":"645409172620611584","lang":"en","tweet_hashtags":[]},{"tweet_urls":[],"text_en":"@Boogie2988 I feel like Dr Ben Carson doesn't get the attention he deserves, instead Trump is making a fool out of the Rep party","created_at":"2015-09-19T21:28:26Z","id":"645409148130103296","lang":"en","tweet_hashtags":[]},{"tweet_urls":[],"text_en":"RT @BracketBattles1: Greatest Active NFL QB\n\u2022 SWEET 16 \u2022\n\nRT ~ Ben Roethlisberger\nFav ~ Carson Palmer http://t.co/5IvCxrIsQM","created_at":"2015-09-19T21:28:18Z","id":"645409115452276736","lang":"en","tweet_hashtags":[]},{"tweet_urls":[],"text_en":"RT @DraftRunBenRun: \"The US should use every resource available to destroy\u201d global jihadists before they destroy the U.S. - Ben Carson","created_at":"2015-09-19T21:28:16Z","id":"645409106539511809","lang":"en","tweet_hashtags":[]},{"tweet_urls":[],"text_en":"RT @DraftRunBenRun: \"My birthday wish is that our nation would once again recognize God as our leader\" - Ben Carson #winbenwin","created_at":"2015-09-19T21:28:07Z","id":"645409067595374592","lang":"en","tweet_hashtags":["winbenwin"]},